{"cameraMode":{"drawMode":0,"name":"Shaded","section":"Shading Mode"},"sceneLighting":true,"audioPlay":false,"sceneViewState":{"m_AlwaysRefresh":false,"showFog":true,"showSkybox":true,"showFlares":true,"showImageEffects":true,"showParticleSystems":true,"showVisualEffectGraphs":true,"m_FxEnabled":true},"in2DMode":false,"pivot":{"x":2.0550763607025148,"y":3.095834732055664,"z":-4.494810104370117},"rotation":{"x":-0.21994268894195558,"y":-0.2633614242076874,"z":0.06153085455298424,"w":-0.9373812675476074},"size":4.581467151641846,"orthographic":false}